printastic/__init__.py
printastic/formatter.py
printastic-0.1.dist-info/METADATA
printastic-0.1.dist-info/WHEEL
printastic-0.1.dist-info/top_level.txt
printastic-0.1.dist-info/RECORD
