Metadata-Version: 2.4
Name: printastic
Version: 0.1
Summary: A pretty fantastic terminal output formatter
Author: Anuj Thapa
Requires-Dist: rich
Dynamic: author
Dynamic: requires-dist
Dynamic: summary
